nautobot_dev_example/__init__.py
nautobot_dev_example/api/__init__.py
nautobot_dev_example/api/serializers.py
nautobot_dev_example/api/urls.py
nautobot_dev_example/api/views.py
nautobot_dev_example/app-config-schema.json
nautobot_dev_example/filters.py
nautobot_dev_example/forms.py
nautobot_dev_example/migrations/0001_initial.py
nautobot_dev_example/migrations/0002_alter_devexample_description_alter_devexample_name.py
nautobot_dev_example/migrations/__init__.py
nautobot_dev_example/models.py
nautobot_dev_example/navigation.py
nautobot_dev_example/tables.py
nautobot_dev_example/tests/__init__.py
nautobot_dev_example/tests/fixtures.py
nautobot_dev_example/tests/test_api.py
nautobot_dev_example/tests/test_filters.py
nautobot_dev_example/tests/test_forms.py
nautobot_dev_example/tests/test_models.py
nautobot_dev_example/tests/test_views.py
nautobot_dev_example/urls.py
nautobot_dev_example/views.py
nautobot_dev_example-2.2.2.dist-info/LICENSE
nautobot_dev_example-2.2.2.dist-info/METADATA
nautobot_dev_example-2.2.2.dist-info/WHEEL
nautobot_dev_example-2.2.2.dist-info/RECORD
