Metadata-Version: 2.3
Name: nautobot-dev-example
Version: 2.2.2
Summary: Nautobot App to demonstrate how to create a Nautobot App.
License: Apache-2.0
Keywords: nautobot,nautobot-app,nautobot-plugin
Author: Network to Code, LLC
Author-email: opensource@networktocode.com
Requires-Python: >=3.9.2,<3.13
Classifier: Development Status :: 5 - Production/Stable
Classifier: Intended Audience :: Developers
Classifier: License :: OSI Approved :: Apache Software License
Classifier: Programming Language :: Python :: 3
Classifier: Programming Language :: Python :: 3.10
Classifier: Programming Language :: Python :: 3.11
Classifier: Programming Language :: Python :: 3.12
Classifier: Programming Language :: Python :: 3.9
Provides-Extra: all
Requires-Dist: nautobot (>=2.4.11,<3.0.0)
Project-URL: Documentation, https://docs.nautobot.com/projects/dev-example/en/latest/
Project-URL: Homepage, https://github.com/nautobot/nautobot-app-dev-example
Project-URL: Repository, https://github.com/nautobot/nautobot-app-dev-example
